<?xml version="1.0" encoding="UTF-8"?>

<configs>

  <append xpath="/items">
    <item name="dutGunMGT3M60Legendary">
      <property name="CreativeMode" value="Player"/>
      
      <property name="CustomIcon" value="gunMGT3M60"/>
      <property name="CustomIconTint" value="FFAF61"/>

      <property name="Tags" value="weapon,ranged,holdBreathAiming,reloadPenalty,gun,barrelAttachments,sideAttachments,smallTopAttachments,magazine,drumMagazine,bottomAttachments,mediumTopAttachments,attFortitude,perkMachineGunner,perkBookAutoWeapons,attachmentsIncluded,canHaveCosmetic,machinegunSkill"/>
      <property name="DisplayType" value="rangedGun"/>
      <property name="HoldType" value="60"/>
      <property name="Meshfile" value="@:Other/Items/Weapons/Ranged/MachineGun/m60MachinegunPrefab.prefab"/>
      <property name="Material" value="MMachineGunParts"/>
      <property name="TintColor" value="FFAF61"/>
      <property name="CrosshairOnAim" value="true"/>
      <!-- aimTest -->
      <property name="CrosshairUpAfterShot" value="true"/>
      <!-- aimTest -->
      <property name="Weight" value="7"/>
      <property name="ScrapTimeOverride" value="10.0"/>
      <property name="RepairTools" value="resourceRepairKit"/>
      <property name="DegradationBreaksAfter" value="false"/>
      <property name="SoundJammed" value="weapon_jam"/>
      <property name="Sound_Sight_In" value="rifle_sight_in"/>
      <property name="Sound_Sight_Out" value="rifle_sight_out"/>
      <property name="RepairExpMultiplier" value="10.8"/>
      <property name="EconomicValue" value="5000"/>
      <property name="TraderStageTemplate" value="baseTier3"/>
      <!-- gunMGT3M60 -->
      <property name="UnlockedBy" value="craftingMachineGuns"/>
      <!-- perkAutoWeaponsMachineGuns, -->
      <property name="ShowQuality" value="false"/> <!-- dutluk -->
      <property name="Group" value="Ammo/Weapons,Ranged Weapons"/>
      <property name="SoundUnholster" value="weapon_unholster"/>
      <property name="SoundHolster" value="weapon_holster"/>
      <property name="SoundPickup" value="rifle_polymer_grab"/>
      <property name="SoundPlace" value="rifle_polymer_place"/>

      <property class="Action0">
        <property name="Class" value="Ranged"/>
        <property name="Delay" value=".150"/>
        <!-- obsolete if rounds per minute exists -->
        <property name="Magazine_items" value="ammo762mmBulletBall,ammo762mmBulletHP,ammo762mmBulletAP"/>
        <property name="Sound_start" value="m60_fire"/>
        <property name="Sound_loop" value="m60_fire"/>
        <property name="Sound_empty" value="dryfire"/>
        <property name="Sound_reload" value="m60_reload"/>
        <property name="Sound_end" value="m60_fire_end"/>
        <property name="AutoReload" value="false"/>
        <property name="Particles_muzzle_fire" value="gunfire_MG_M60"/>
        <property name="triggerEffectTriggerPullDualsense" value="RifleTrigger"/>
        <property name="triggerEffectTriggerPullXbox" value="PistolTrigger"/>
        <property name="triggerEffectTriggerShootDualsense" value="MGShoot"/>
        <property name="triggerEffectTriggerShootXbox" value="PistolShoot"/>
      </property>
      <property class="Action1">
        <property name="Class" value="Zoom"/>
        <property name="Zoom_max_out" value="55"/>
        <property name="Zoom_max_in" value="55"/>
        <property name="SightsCameraOffset" value="-.00062,0,.055"/>
        <property name="zoomTriggerEffectTriggerPullDualsense" value="RifleZoom"/>
        <property name="zoomTriggerEffectTriggerPullXbox" value="PistolZoom"/>
      </property>

      <effect_group name="dutGunMGT3M60Legendary">
        <passive_effect name="MaxRange" operation="base_set" value="90" tags="perkMachineGunner"/>
        <passive_effect name="DamageFalloffRange" operation="base_set" value="58" tags="perkMachineGunner"/>
        <passive_effect name="DamageFalloffRange" operation="perc_add" value=".05" tags="perkMachineGunner"/>
        <!-- random effective rng -->
        <passive_effect name="BlockDamage" operation="base_add" value="-2" tags="perkMachineGunner"/>
        <!-- damage offset -->
        <passive_effect name="EntityDamage" operation="base_add" value="30" tags="perkMachineGunner"/>
        <!-- damage offset -->
        <passive_effect name="EntityDamage" operation="perc_add" value=".01,.25" tags="perkMachineGunner"/>
        <!-- random BlockDmg -->
        <passive_effect name="BlockDamage" operation="perc_add" value=".75" tags="perkMachineGunner"/>
        <!-- tier bonus -->
        <passive_effect name="WeaponHandling" operation="perc_add" value=".08" tags="perkMachineGunner"/>
        <!-- random WeaponHandling -->
        <passive_effect name="RoundsPerMinute" operation="base_set" value="440" tags="perkMachineGunner"/>
        <passive_effect name="BurstRoundCount" operation="base_set" value="1000" tags="perkMachineGunner"/>
        <passive_effect name="MagazineSize" operation="base_set" value="60" tags="perkMachineGunner"/>
        <passive_effect name="MagazineSize" operation="base_add" value="1,15" tags="perkMachineGunner"/>
        <passive_effect name="ReloadSpeedMultiplier" operation="base_set" value="1" tags="perkMachineGunner"/>

        <passive_effect name="SpreadDegreesVertical" operation="base_set" value="2.8" tags="perkMachineGunner"/>
        <passive_effect name="SpreadDegreesHorizontal" operation="base_set" value="2.8" tags="perkMachineGunner"/>
        <passive_effect name="SpreadMultiplierAiming" operation="base_set" value=".33" tags="perkMachineGunner"/>
        <passive_effect name="SpreadMultiplierCrouching" operation="base_set" value=".8" tags="perkMachineGunner"/>
        <passive_effect name="SpreadMultiplierWalking" operation="base_set" value="1.5" tags="perkMachineGunner"/>
        <passive_effect name="SpreadMultiplierRunning" operation="base_set" value="2.2" tags="perkMachineGunner"/>

        <passive_effect name="KickDegreesVerticalMin" operation="base_set" value="-.4" tags="perkMachineGunner"/>
        <passive_effect name="KickDegreesVerticalMax" operation="base_set" value="1.1" tags="perkMachineGunner"/>
        <passive_effect name="KickDegreesHorizontalMin" operation="base_set" value="-1" tags="perkMachineGunner"/>
        <passive_effect name="KickDegreesHorizontalMax" operation="base_set" value="1" tags="perkMachineGunner"/>

        <passive_effect name="IncrementalSpreadMultiplier" operation="base_set" value="1.5" tags="perkMachineGunner"/>
        <passive_effect name="WeaponHandling" operation="base_set" value=".83" tags="perkMachineGunner"/>
        <!-- M60 -->

        <passive_effect name="DegradationMax" operation="base_set" value="1100" tags="perkMachineGunner,perkBookAutoWeapons"/>
        <passive_effect name="DegradationPerUse" operation="base_set" value="1" tags="perkMachineGunner,perkBookAutoWeapons"/>

        <passive_effect name="ModSlots" operation="base_set" value="4" tier="1"/>
        <passive_effect name="ModPowerBonus" operation="perc_add" value=".10" tags="EntityDamage,BlockDamage"/>
        <passive_effect name="ModPowerBonus" operation="base_add" value="300" tags="EconomicValue"/>
      </effect_group>
    </item>

  </append>

</configs>
